secretting/__init__.py
secretting-1.6.1.dist-info/METADATA
secretting-1.6.1.dist-info/WHEEL
secretting-1.6.1.dist-info/top_level.txt
secretting-1.6.1.dist-info/RECORD
