Metadata-Version: 2.4
Name: secretting
Version: 1.6.1
Summary: More secrets and randoms!
Dynamic: description
Dynamic: description-content-type
Dynamic: summary
